{
    "task_params": {
        "add_self_loop_edges": false
    },
    "model_params": {
        "max_nodes_in_batch": 50000,
        "graph_num_layers": 8,
        "graph_num_timesteps_per_layer": 1,
        "graph_layer_input_dropout_keep_prob": 0.9,
        "graph_dense_between_every_num_gnn_layers": 1,
        "graph_model_activation_function": "tanh",
        "graph_residual_connection_every_num_layers": 2,
        "graph_inter_layer_norm": true,
        "max_epochs": 10000,
        "patience": 5,
        "optimizer": "Adam",
        "learning_rate": 0.00015,
        "learning_rate_decay": 0.98,
        "lr_for_num_graphs_per_batch": 30,
        "momentum": 0.85,
        "clamp_gradient_norm": 1.0,
        "random_seed": 0,
        "hidden_size": 128,
        "graph_activation_function": "gelu",
        "message_aggregation_function": "sum",
        "graph_message_weights_dropout_ratio": 0.0,
        "use_target_state_as_input": true,
        "num_edge_hidden_layers": 0
    }
}